mfem/__init__.py
mfem/__sha__.py
mfem/par.py
mfem/ser.py
mfem/_par/__init__.py
mfem/_par/array.i
mfem/_par/arrays_by_name.i
mfem/_par/attribute_sets.i
mfem/_par/auxiliary.i
mfem/_par/bilinearform.i
mfem/_par/bilininteg.i
mfem/_par/blockmatrix.i
mfem/_par/blockoperator.i
mfem/_par/blockvector.i
mfem/_par/bounds.i
mfem/_par/coefficient.i
mfem/_par/coefficient_py.cpp
mfem/_par/coefficient_py.hpp
mfem/_par/common_functions.i
mfem/_par/communication.i
mfem/_par/complex_fem.i
mfem/_par/complex_operator.i
mfem/_par/constraints.i
mfem/_par/cpointers.i
mfem/_par/datacollection.i
mfem/_par/densemat.i
mfem/_par/device.i
mfem/_par/dist_solver.i
mfem/_par/doftrans.i
mfem/_par/element.i
mfem/_par/eltrans.i
mfem/_par/enzyme.i
mfem/_par/error.i
mfem/_par/estimators.i
mfem/_par/fe.i
mfem/_par/fe_base.i
mfem/_par/fe_coll.i
mfem/_par/fe_fixed_order.i
mfem/_par/fe_h1.i
mfem/_par/fe_l2.i
mfem/_par/fe_nd.i
mfem/_par/fe_nurbs.i
mfem/_par/fe_pos.i
mfem/_par/fe_rt.i
mfem/_par/fe_ser.i
mfem/_par/fespace.i
mfem/_par/fespacehierarchy.i
mfem/_par/geom.i
mfem/_par/globals.i
mfem/_par/gridfunc.i
mfem/_par/gslib.i
mfem/_par/handle.i
mfem/_par/hash.i
mfem/_par/hexahedron.i
mfem/_par/hybridization.i
mfem/_par/hyperbolic.i
mfem/_par/hypre.i
mfem/_par/integrator.i
mfem/_par/intrules.i
mfem/_par/intrules_cut.i
mfem/_par/io_stream.i
mfem/_par/iostream_typemap.hpp
mfem/_par/istream_typemap.i
mfem/_par/linearform.i
mfem/_par/lininteg.i
mfem/_par/matrix.i
mfem/_par/mem_manager.i
mfem/_par/mesh.i
mfem/_par/mesh_operators.i
mfem/_par/multigrid.i
mfem/_par/navier_solver.i
mfem/_par/ncmesh.i
mfem/_par/nonlinearform.i
mfem/_par/nonlininteg.i
mfem/_par/ode.i
mfem/_par/operators.i
mfem/_par/ostream_typemap.i
mfem/_par/pbilinearform.i
mfem/_par/pfespace.i
mfem/_par/pgridfunc.i
mfem/_par/plinearform.i
mfem/_par/pmesh.i
mfem/_par/pncmesh.i
mfem/_par/pnonlinearform.i
mfem/_par/point.i
mfem/_par/prestriction.i
mfem/_par/psubmesh.i
mfem-4.8.0.1.dist-info/METADATA
mfem-4.8.0.1.dist-info/WHEEL
mfem-4.8.0.1.dist-info/top_level.txt
mfem-4.8.0.1.dist-info/RECORD
mfem-4.8.0.1.dist-info/licenses/LICENSE
