Metadata-Version: 2.4
Name: mfem
Version: 4.8.0.1
Summary: MFEM + PyMFEM (finite element method library)
Author: MFEM development team
Maintainer-email: "S. Shiraiwa" <shiraiwa@princeton.edu>
License-Expression: BSD-3-Clause
Project-URL: Homepage, http://mfem.org
Project-URL: Download, https://github.com/pymfem
Keywords: scientific computing,finite element method
Classifier: Development Status :: 5 - Production/Stable
Classifier: Intended Audience :: Developers
Classifier: Topic :: Scientific/Engineering :: Physics
Classifier: Programming Language :: Python :: 3.9
Classifier: Programming Language :: Python :: 3.10
Classifier: Programming Language :: Python :: 3.11
Classifier: Programming Language :: Python :: 3.12
Classifier: Programming Language :: Python :: 3.13
Requires-Python: >=3.8
License-File: LICENSE
Requires-Dist: numpy>=2.0.0
Requires-Dist: numba
Requires-Dist: scipy
Provides-Extra: mpi
Requires-Dist: mpi4py; extra == "mpi"
Dynamic: license-file
